{
    "AITKIN": [
        "MN0010000",
        "MN0010100",
        "MN0010200",
        "MN0010400"
    ],
    "ANOKA": [
        "MN0020000",
        "MN0020100",
        "MN0020200",
        "MN0020300",
        "MN0020400",
        "MN0020500",
        "MN0020600",
        "MN0020700",
        "MN0021300",
        "MN0021500"
    ],
    "RAMSEY; ANOKA": [
        "MN0020800"
    ],
    "BECKER": [
        "MN0030000",
        "MN0030100",
        "MN0030200",
        "MN0030300",
        "MN0030400",
        "MN0030900",
        "MNMHP0800"
    ],
    "BELTRAMI": [
        "MN0040000",
        "MN0040100",
        "MN0040200"
    ],
    "BENTON": [
        "MN0050000",
        "MN0050100",
        "MN0050200",
        "MN0050300"
    ],
    "BIG STONE": [
        "MN0060000",
        "MN0060100"
    ],
    "BLUE EARTH": [
        "MN0070000",
        "MN0070100",
        "MN0070200",
        "MN0070400",
        "MN0070500",
        "MN0071000",
        "MNMHP1200"
    ],
    "BROWN": [
        "MN0080000",
        "MN0080100",
        "MN0080200",
        "MN0080300"
    ],
    "COTTONWOOD; BROWN": [
        "MN0080400"
    ],
    "CARLTON": [
        "MN0090000",
        "MN0090100",
        "MN0090200"
    ],
    "CARVER": [
        "MN0100000",
        "MN0100200"
    ],
    "CASS": [
        "MN0110000",
        "MN0110200",
        "MN0110500",
        "MN0110700",
        "MN0110800",
        "MN0111000"
    ],
    "CHIPPEWA": [
        "MN0120000",
        "MN0120100",
        "MN0120200"
    ],
    "CHISAGO": [
        "MN0130000",
        "MN0130500",
        "MN0130800",
        "MN0130900"
    ],
    "CLAY": [
        "MN0140000",
        "MN0140100",
        "MN0140200",
        "MN0140300",
        "MN0140400",
        "MN0140600"
    ],
    "CLEARWATER": [
        "MN0150000",
        "MN0150100",
        "MN0150200"
    ],
    "COOK": [
        "MN0160000"
    ],
    "COTTONWOOD": [
        "MN0170000",
        "MN0170100",
        "MN0170200",
        "MN0170500"
    ],
    "CROW WING": [
        "MN0180000",
        "MN0180100",
        "MN0180200",
        "MN0180300",
        "MN0180400",
        "MN0180500",
        "MN0180600",
        "MN0180700",
        "MN0181000",
        "MN0181100",
        "MN0181300",
        "MNMHP0700"
    ],
    "DAKOTA": [
        "MN0190000",
        "MN0190100",
        "MN0190200",
        "MN0190400",
        "MN0190500",
        "MN0190600",
        "MN0190700",
        "MN0190800",
        "MN0190900",
        "MN0191000",
        "MN0191100"
    ],
    "WASHINGTON; DAKOTA": [
        "MN0190300"
    ],
    "DODGE": [
        "MN0200000",
        "MN0200200",
        "MN0200600"
    ],
    "DOUGLAS": [
        "MN0210000",
        "MN0210100"
    ],
    "TODD; DOUGLAS": [
        "MN0210200"
    ],
    "FARIBAULT": [
        "MN0220000",
        "MN0220100",
        "MN0220200",
        "MN0220400",
        "MN0220500",
        "MN0221000"
    ],
    "FILLMORE": [
        "MN0230000",
        "MN0230400",
        "MN0230500"
    ],
    "OLMSTED; FILLMORE": [
        "MN0230100"
    ],
    "FREEBORN": [
        "MN0240000",
        "MN0240100"
    ],
    "GOODHUE": [
        "MN0250000",
        "MN0250100",
        "MN0250300",
        "MN0250400",
        "MN0250600",
        "MN0250800"
    ],
    "GRANT": [
        "MN0260000"
    ],
    "HENNEPIN": [
        "MN0270000",
        "MN0270100",
        "MN0270200",
        "MN0270300",
        "MN0270400",
        "MN0270500",
        "MN0270600",
        "MN0270700",
        "MN0270800",
        "MN0270900",
        "MN0271100",
        "MN0271200",
        "MN0271400",
        "MN0271500",
        "MN0271600",
        "MN0271700",
        "MN0271800",
        "MN0271900",
        "MN0272100",
        "MN0272300",
        "MN0272400",
        "MN0272500",
        "MN0272600",
        "MN0272700",
        "MN0272800",
        "MN0272900",
        "MN0273000",
        "MN0273100",
        "MN0273400",
        "MN0273700",
        "MN0274000",
        "MN0274300",
        "MNMHP0400"
    ],
    "RAMSEY; HENNEPIN": [
        "MN0272000"
    ],
    "WRIGHT; HENNEPIN": [
        "MN0273200"
    ],
    "HOUSTON": [
        "MN0280000",
        "MN0280100",
        "MN0280200",
        "MN0280300",
        "MN0280400",
        "MN0280500"
    ],
    "HUBBARD": [
        "MN0290000",
        "MN0290100",
        "MN0290200"
    ],
    "ISANTI": [
        "MN0300000",
        "MN0300100",
        "MN0300200",
        "MN0300300"
    ],
    "ITASCA": [
        "MN0310000",
        "MN0310100",
        "MN0310200",
        "MN0310300",
        "MN0310400",
        "MN0310500",
        "MN0310700"
    ],
    "JACKSON": [
        "MN0320000",
        "MN0320200",
        "MN0320300"
    ],
    "KANABEC": [
        "MN0330000"
    ],
    "KANDIYOHI": [
        "MN0340000",
        "MN0340100",
        "MN0340200"
    ],
    "KITTSON": [
        "MN0350000",
        "MN0350100"
    ],
    "KOOCHICHING": [
        "MN0360000",
        "MN0360100"
    ],
    "LAC QUI PARLE": [
        "MN0370000",
        "MN0370100"
    ],
    "LAKE": [
        "MN0380000",
        "MN0380100",
        "MN0380200"
    ],
    "LAKE OF THE WOODS": [
        "MN0390000"
    ],
    "LE SUEUR": [
        "MN0400000",
        "MN0400100",
        "MN0400200",
        "MN0400300",
        "MN0400400",
        "MN0400600"
    ],
    "LINCOLN": [
        "MN0410000",
        "MN0410100",
        "MN0410400"
    ],
    "LYON": [
        "MN0420000",
        "MN0420100",
        "MN0420200",
        "MN0420300",
        "MNMHP0300"
    ],
    "MCLEOD": [
        "MN0430000",
        "MN0430100",
        "MN0430200",
        "MN0430300",
        "MN0430400",
        "MN0430700"
    ],
    "MAHNOMEN": [
        "MN0440000"
    ],
    "MARSHALL": [
        "MN0450000"
    ],
    "MARTIN": [
        "MN0460000",
        "MN0460100",
        "MN0460200",
        "MN0460300",
        "MN0460700"
    ],
    "MEEKER": [
        "MN0470000",
        "MN0470100"
    ],
    "STEARNS; MEEKER": [
        "MN0470200"
    ],
    "MILLE LACS": [
        "MN0480000",
        "MN0480100",
        "MN0480300",
        "MN0480400"
    ],
    "SHERBURNE; MILLE LACS": [
        "MN0480200"
    ],
    "MORRISON": [
        "MN0490000",
        "MN0490100",
        "MN0490300",
        "MN0490500"
    ],
    "CASS; MORRISON": [
        "MN0490200"
    ],
    "MOWER": [
        "MN0500000",
        "MN0500100"
    ],
    "MURRAY": [
        "MN0510000",
        "MN0510100",
        "MN0510200"
    ],
    "NICOLLET": [
        "MN0520000",
        "MN0520100",
        "MN0520200"
    ],
    "NOBLES": [
        "MN0530000",
        "MN0530100",
        "MN0530200"
    ],
    "NORMAN": [
        "MN0540000",
        "MN0540100",
        "MN0540400"
    ],
    "OLMSTED": [
        "MN0550000",
        "MN0550100",
        "MNMHP0200"
    ],
    "OTTER TAIL": [
        "MN0560000",
        "MN0560100",
        "MN0560200",
        "MN0560300",
        "MN0560400",
        "MN0560600",
        "MN0560700",
        "MN0560800"
    ],
    "PENNINGTON": [
        "MN0570000",
        "MN0570100",
        "MNMHP0900"
    ],
    "PINE": [
        "MN0580000"
    ],
    "PIPESTONE": [
        "MN0590000"
    ],
    "POLK": [
        "MN0600000",
        "MN0600100",
        "MN0600200",
        "MN0601300"
    ],
    "POPE": [
        "MN0610000",
        "MN0610100",
        "MN0610200"
    ],
    "RAMSEY": [
        "MN0620000",
        "MN0620300",
        "MN0620400",
        "MN0620500",
        "MN0620600",
        "MN0620700",
        "MN0620800",
        "MN0620900",
        "MN0622000",
        "MNMHP0100",
        "MNMHP1300"
    ],
    "WASHINGTON; RAMSEY": [
        "MN0621000"
    ],
    "RED LAKE": [
        "MN0630000"
    ],
    "REDWOOD": [
        "MN0640000",
        "MN0640100",
        "MN0640200",
        "MN0640400",
        "MN0640700"
    ],
    "RENVILLE": [
        "MN0650000",
        "MN0650100",
        "MN0650200",
        "MN0650300",
        "MN0650400",
        "MN0650600",
        "MN0650700"
    ],
    "RICE": [
        "MN0660000",
        "MN0660100",
        "MN0660300",
        "MN0660400"
    ],
    "DAKOTA; RICE": [
        "MN0660200"
    ],
    "ROCK": [
        "MN0670000"
    ],
    "ROSEAU": [
        "MN0680000",
        "MN0680100",
        "MN0680200"
    ],
    "ST LOUIS": [
        "MN0690000",
        "MN0690200",
        "MN0690500",
        "MN0690600",
        "MN0690700",
        "MN0690800",
        "MN0690900",
        "MN0691000",
        "MN0691300",
        "MN0691400",
        "MN0691500",
        "MN0691700",
        "MN0691800",
        "MN0692100",
        "MN0694400",
        "MNMHP1000",
        "MNMHP1100"
    ],
    "SCOTT": [
        "MN0700000",
        "MN0700100",
        "MN0700200",
        "MN0700400",
        "MN0700600",
        "MN0700900",
        "MN0701000"
    ],
    "LE SUEUR; SCOTT": [
        "MN0700300"
    ],
    "SHERBURNE": [
        "MN0710000",
        "MN0710100",
        "MN0710200",
        "MN0710400"
    ],
    "SIBLEY": [
        "MN0720000",
        "MN0720100",
        "MN0720200",
        "MN0720400",
        "MN0720500",
        "MN0720600"
    ],
    "STEARNS": [
        "MN0730000",
        "MN0730100",
        "MN0730200",
        "MN0730300",
        "MN0730500",
        "MN0730600",
        "MN0730800",
        "MN0731100",
        "MN0731400",
        "MN0731600",
        "MNMHP0600"
    ],
    "BENTON; SHERBURNE; STEARNS": [
        "MN0730400"
    ],
    "BENTON; STEARNS": [
        "MN0731200"
    ],
    "STEELE": [
        "MN0740000",
        "MN0740100",
        "MN0740200"
    ],
    "STEVENS": [
        "MN0750000",
        "MN0750100",
        "MN0750600"
    ],
    "SWIFT": [
        "MN0760000",
        "MN0760100",
        "MN0760200"
    ],
    "TODD": [
        "MN0770000",
        "MN0770100"
    ],
    "WADENA; TODD": [
        "MN0770200"
    ],
    "TRAVERSE": [
        "MN0780000",
        "MN0780200"
    ],
    "WABASHA": [
        "MN0790000",
        "MN0790200",
        "MN0790300"
    ],
    "GOODHUE; WABASHA": [
        "MN0790100"
    ],
    "WADENA": [
        "MN0800000",
        "MN0800200",
        "MN0800300",
        "MN0800400"
    ],
    "OTTER TAIL; WADENA": [
        "MN0800100"
    ],
    "WASECA": [
        "MN0810000",
        "MN0810100",
        "MN0810200",
        "MN0810300"
    ],
    "WASHINGTON": [
        "MN0820000",
        "MN0820100",
        "MN0820200",
        "MN0820500",
        "MN0820600",
        "MN0820700",
        "MN0820800",
        "MN0821100",
        "MN0821400"
    ],
    "WATONWAN": [
        "MN0830000",
        "MN0830100",
        "MN0830200"
    ],
    "WILKIN": [
        "MN0840000",
        "MN0840100"
    ],
    "WINONA": [
        "MN0850000",
        "MN0850100",
        "MN0850200",
        "MN0850300",
        "MN0850400"
    ],
    "WRIGHT": [
        "MN0860000",
        "MN0860100",
        "MN0860400",
        "MN0860600"
    ],
    "YELLOW MEDICINE": [
        "MN0870000",
        "MN0870100"
    ],
    "CHIPPEWA; YELLOW MEDICINE": [
        "MN0870200"
    ]
}